Metadata-Version: 1.0
Name: iiifree
Version: 1.0.1
Summary: 这是一个网络工程春的库
Home-page: UNKNOWN
Author: free
Author-email: UNKNOWN
License: UNKNOWN
Platform: UNKNOWN
